pcaptoparquet_cli.py
pcaptoparquet/__init__.py
pcaptoparquet/e2e_cli.py
pcaptoparquet/e2e_config.py
pcaptoparquet/e2e_dns.py
pcaptoparquet/e2e_http.py
pcaptoparquet/e2e_https.py
pcaptoparquet/e2e_packet.py
pcaptoparquet/e2e_parallel.py
pcaptoparquet/e2e_pcap.py
pcaptoparquet/e2e_ping.py
pcaptoparquet/e2e_quic.py
pcaptoparquet/e2e_tls_utils.py
pcaptoparquet/e2e_tunnel.py
pcaptoparquet-0.1.20250609.dist-info/licenses/LICENSE
pcaptoparquet-0.1.20250609.dist-info/METADATA
pcaptoparquet-0.1.20250609.dist-info/WHEEL
pcaptoparquet-0.1.20250609.dist-info/entry_points.txt
pcaptoparquet-0.1.20250609.dist-info/top_level.txt
pcaptoparquet-0.1.20250609.dist-info/RECORD
