Metadata-Version: 2.4
Name: pcaptoparquet
Version: 0.1.20250609
Summary: A package for converting pcap files to parquet format.
Author-email: Pablo Rojo <pablo.rojo@nokia.com>
License: BSD 3-Clause License
Project-URL: Homepage, https://github.com/nokia/pcaptoparquet
Project-URL: Issues, https://github.com/nokia/pcaptoparquet/issues
Keywords: pcap,parquet,csv,json
Classifier: Development Status :: 4 - Beta
Classifier: Programming Language :: Python
License-File: LICENSE
Requires-Dist: dpkt
Requires-Dist: cryptography
Requires-Dist: psutil
Requires-Dist: polars
Dynamic: license-file
